odoo/addons/web_save_discard_button/README.rst
odoo/addons/web_save_discard_button/__init__.py
odoo/addons/web_save_discard_button/__manifest__.py
odoo/addons/web_save_discard_button/i18n/es.po
odoo/addons/web_save_discard_button/i18n/fr.po
odoo/addons/web_save_discard_button/i18n/it.po
odoo/addons/web_save_discard_button/i18n/web_save_discard_button.pot
odoo/addons/web_save_discard_button/models/__init__.py
odoo/addons/web_save_discard_button/models/ir_http.py
odoo/addons/web_save_discard_button/readme/CONTRIBUTORS.md
odoo/addons/web_save_discard_button/readme/DESCRIPTION.md
odoo/addons/web_save_discard_button/static/description/icon.png
odoo/addons/web_save_discard_button/static/description/index.html
odoo/addons/web_save_discard_button/static/description/save_button.png
odoo/addons/web_save_discard_button/static/src/xml/template.xml
odoo_addon_web_save_discard_button-18.0.1.0.1.dist-info/METADATA
odoo_addon_web_save_discard_button-18.0.1.0.1.dist-info/WHEEL
odoo_addon_web_save_discard_button-18.0.1.0.1.dist-info/top_level.txt
odoo_addon_web_save_discard_button-18.0.1.0.1.dist-info/RECORD
